TRSFX/__init__.py
TRSFX/_utils/__init__.py
TRSFX/_utils/h5_io.py
TRSFX/_utils/list_io.py
TRSFX/_utils/stream_io.py
TRSFX/compare/__init__.py
TRSFX/compare/cli.py
TRSFX/compare/hd5_corr.py
TRSFX/compare/map_corr.py
TRSFX/explore/__init__.py
TRSFX/explore/cli.py
TRSFX/explore/indexing_related.py
TRSFX/explore/stream.py
TRSFX/indexer/__init__.py
TRSFX/indexer/_configs.py
TRSFX/indexer/_utils.py
TRSFX/indexer/cli.py
TRSFX/indexer/crystfel_detector.py
TRSFX/indexer/crystfel_gridsearch.py
TRSFX/indexer/crystfel_indexing.py
TRSFX/indexer/crystfel_merging.py
TRSFX/manipulation/__init__.py
TRSFX/manipulation/cli.py
TRSFX/manipulation/crystfel_to_meteor.py
TRSFX/manipulation/sample_stream.py
trsfx-0.4.0.dist-info/licenses/LICENSE
trsfx-0.4.0.dist-info/METADATA
trsfx-0.4.0.dist-info/WHEEL
trsfx-0.4.0.dist-info/entry_points.txt
trsfx-0.4.0.dist-info/top_level.txt
trsfx-0.4.0.dist-info/RECORD
