Metadata-Version: 2.4
Name: TRSFX
Version: 0.4.0
Summary: Crystallographic Utilities from the Standfuss group out of PSI
Author-email: Ryan O'Dea <ryan.odea@psi.ch>
Maintainer-email: Ryan O'Dea <ryan.odea@psi.ch>
Project-URL: repository, https://github.com/ryan-odea/TRSFX
Classifier: Development Status :: 4 - Beta
Classifier: Intended Audience :: Science/Research
Classifier: License :: OSI Approved :: MIT License
Classifier: Operating System :: OS Independent
Classifier: Programming Language :: Python :: 3
Classifier: Programming Language :: Python :: 3.11
Classifier: Programming Language :: Python :: 3.12
Classifier: Topic :: Scientific/Engineering :: Bio-Informatics
Classifier: Topic :: Scientific/Engineering :: Chemistry
Classifier: Topic :: Scientific/Engineering :: Physics
Classifier: Typing :: Typed
Requires-Python: >=3.8
License-File: LICENSE
Requires-Dist: storageCat>=1.0.2
Requires-Dist: hatTrick>=0.2.1
Requires-Dist: meteor-maps>=0.4.0
Requires-Dist: reciprocalspaceship>=1.0.7
Requires-Dist: click>=8.3.1
Requires-Dist: seaborn>=0.13.2
Requires-Dist: matplotlib>=3.10.7
Requires-Dist: numpy>=2.3.5
Requires-Dist: gemmi>=0.7.3
Requires-Dist: natsort>=8.4.0
Requires-Dist: pandas>=2.3.3
Requires-Dist: submitit>=1.5.1
Requires-Dist: h5py>=3.11.0
Requires-Dist: hdf5plugin>=6.0.0
Dynamic: license-file
